{
  "181": [
    "What made Baghdad such an important city from the 8th to 13th centuries?",
    "What was the House of Wisdom, and what happened there?"
  ],
  "182": [
    "Why didn't merchants travel the entire length of the Silk Road?",
    "What besides goods traveled along the Silk Road?"
  ],
  "183": [
    "What Arabic word gave us the term 'algebra,' and what does it mean?",
    "How did al-Khwarizmi's name give us the word 'algorithm'?"
  ],
  "184": [
    "Why did calligraphy become such an important art in Islamic culture?",
    "Name two different styles of Arabic script and describe how they were used."
  ],
  "186": [
    "How were Arabian hospitals in the 9th-10th centuries different from medical care in Europe at the same time?",
    "Name one important contribution Arabian physicians made to medical knowledge."
  ],
  "187": [
    "Why were spices so valuable in medieval times?",
    "How did the spice trade change world history?"
  ],
  "188": [
    "What opportunities for education existed in medieval Baghdad, even for poor families?",
    "What did scholars at the House of Wisdom do with the texts they translated?"
  ]
}
