{
  "generatedAt": "2026-07-06T12:49:45.121Z",
  "summary": {
    "gradesWithPocketMaps": [
      1,
      2,
      3,
      4,
      5,
      6,
      7,
      8
    ],
    "cardCount": 94,
    "cardsByGrade": {
      "1": 6,
      "2": 29,
      "3": 12,
      "4": 9,
      "5": 11,
      "6": 8,
      "7": 7,
      "8": 12
    }
  },
  "gradeDayFiles": {
    "grade-1": {
      "uniqueDayCount": 180,
      "missing": [],
      "extras": [],
      "duplicateDayFiles": []
    },
    "grade-2": {
      "uniqueDayCount": 180,
      "missing": [],
      "extras": [],
      "duplicateDayFiles": []
    },
    "grade-3": {
      "uniqueDayCount": 180,
      "missing": [],
      "extras": [],
      "duplicateDayFiles": []
    },
    "grade-4": {
      "uniqueDayCount": 180,
      "missing": [],
      "extras": [],
      "duplicateDayFiles": [
        {
          "day": 1,
          "files": [
            "4th-grade-day-001.html",
            "4th-grade-day-1.html"
          ]
        },
        {
          "day": 2,
          "files": [
            "4th-grade-day-002.html",
            "4th-grade-day-2.html"
          ]
        },
        {
          "day": 3,
          "files": [
            "4th-grade-day-003.html",
            "4th-grade-day-3.html"
          ]
        },
        {
          "day": 4,
          "files": [
            "4th-grade-day-004.html",
            "4th-grade-day-4.html"
          ]
        },
        {
          "day": 5,
          "files": [
            "4th-grade-day-005.html",
            "4th-grade-day-5.html"
          ]
        },
        {
          "day": 6,
          "files": [
            "4th-grade-day-006.html",
            "4th-grade-day-6.html"
          ]
        },
        {
          "day": 7,
          "files": [
            "4th-grade-day-007.html",
            "4th-grade-day-7.html"
          ]
        },
        {
          "day": 8,
          "files": [
            "4th-grade-day-008.html",
            "4th-grade-day-8.html"
          ]
        },
        {
          "day": 9,
          "files": [
            "4th-grade-day-009.html",
            "4th-grade-day-9.html"
          ]
        },
        {
          "day": 10,
          "files": [
            "4th-grade-day-010.html",
            "4th-grade-day-10.html"
          ]
        },
        {
          "day": 11,
          "files": [
            "4th-grade-day-011.html",
            "4th-grade-day-11.html"
          ]
        },
        {
          "day": 12,
          "files": [
            "4th-grade-day-012.html",
            "4th-grade-day-12.html"
          ]
        },
        {
          "day": 13,
          "files": [
            "4th-grade-day-013.html",
            "4th-grade-day-13.html"
          ]
        },
        {
          "day": 14,
          "files": [
            "4th-grade-day-014.html",
            "4th-grade-day-14.html"
          ]
        },
        {
          "day": 15,
          "files": [
            "4th-grade-day-015.html",
            "4th-grade-day-15.html"
          ]
        },
        {
          "day": 16,
          "files": [
            "4th-grade-day-016.html",
            "4th-grade-day-16.html"
          ]
        },
        {
          "day": 17,
          "files": [
            "4th-grade-day-017.html",
            "4th-grade-day-17.html"
          ]
        },
        {
          "day": 18,
          "files": [
            "4th-grade-day-018.html",
            "4th-grade-day-18.html"
          ]
        },
        {
          "day": 19,
          "files": [
            "4th-grade-day-019.html",
            "4th-grade-day-19.html"
          ]
        },
        {
          "day": 20,
          "files": [
            "4th-grade-day-020.html",
            "4th-grade-day-20.html"
          ]
        },
        {
          "day": 21,
          "files": [
            "4th-grade-day-021.html",
            "4th-grade-day-21.html"
          ]
        },
        {
          "day": 22,
          "files": [
            "4th-grade-day-022.html",
            "4th-grade-day-22.html"
          ]
        },
        {
          "day": 23,
          "files": [
            "4th-grade-day-023.html",
            "4th-grade-day-23.html"
          ]
        },
        {
          "day": 24,
          "files": [
            "4th-grade-day-024.html",
            "4th-grade-day-24.html"
          ]
        },
        {
          "day": 25,
          "files": [
            "4th-grade-day-025.html",
            "4th-grade-day-25.html"
          ]
        },
        {
          "day": 26,
          "files": [
            "4th-grade-day-026.html",
            "4th-grade-day-26.html"
          ]
        },
        {
          "day": 27,
          "files": [
            "4th-grade-day-027.html",
            "4th-grade-day-27.html"
          ]
        },
        {
          "day": 28,
          "files": [
            "4th-grade-day-028.html",
            "4th-grade-day-28.html"
          ]
        },
        {
          "day": 29,
          "files": [
            "4th-grade-day-029.html",
            "4th-grade-day-29.html"
          ]
        },
        {
          "day": 30,
          "files": [
            "4th-grade-day-030.html",
            "4th-grade-day-30.html"
          ]
        },
        {
          "day": 31,
          "files": [
            "4th-grade-day-031.html",
            "4th-grade-day-31.html"
          ]
        },
        {
          "day": 32,
          "files": [
            "4th-grade-day-032.html",
            "4th-grade-day-32.html"
          ]
        },
        {
          "day": 33,
          "files": [
            "4th-grade-day-033.html",
            "4th-grade-day-33.html"
          ]
        },
        {
          "day": 34,
          "files": [
            "4th-grade-day-034.html",
            "4th-grade-day-34.html"
          ]
        },
        {
          "day": 35,
          "files": [
            "4th-grade-day-035.html",
            "4th-grade-day-35.html"
          ]
        },
        {
          "day": 36,
          "files": [
            "4th-grade-day-036.html",
            "4th-grade-day-36.html"
          ]
        },
        {
          "day": 37,
          "files": [
            "4th-grade-day-037.html",
            "4th-grade-day-37.html"
          ]
        },
        {
          "day": 38,
          "files": [
            "4th-grade-day-038.html",
            "4th-grade-day-38.html"
          ]
        },
        {
          "day": 39,
          "files": [
            "4th-grade-day-039.html",
            "4th-grade-day-39.html"
          ]
        },
        {
          "day": 40,
          "files": [
            "4th-grade-day-040.html",
            "4th-grade-day-40.html"
          ]
        },
        {
          "day": 41,
          "files": [
            "4th-grade-day-041.html",
            "4th-grade-day-41.html"
          ]
        },
        {
          "day": 42,
          "files": [
            "4th-grade-day-042.html",
            "4th-grade-day-42.html"
          ]
        },
        {
          "day": 43,
          "files": [
            "4th-grade-day-043.html",
            "4th-grade-day-43.html"
          ]
        },
        {
          "day": 44,
          "files": [
            "4th-grade-day-044.html",
            "4th-grade-day-44.html"
          ]
        },
        {
          "day": 45,
          "files": [
            "4th-grade-day-045.html",
            "4th-grade-day-45.html"
          ]
        },
        {
          "day": 46,
          "files": [
            "4th-grade-day-046.html",
            "4th-grade-day-46.html"
          ]
        },
        {
          "day": 47,
          "files": [
            "4th-grade-day-047.html",
            "4th-grade-day-47.html"
          ]
        },
        {
          "day": 48,
          "files": [
            "4th-grade-day-048.html",
            "4th-grade-day-48.html"
          ]
        },
        {
          "day": 49,
          "files": [
            "4th-grade-day-049.html",
            "4th-grade-day-49.html"
          ]
        },
        {
          "day": 50,
          "files": [
            "4th-grade-day-050.html",
            "4th-grade-day-50.html"
          ]
        },
        {
          "day": 51,
          "files": [
            "4th-grade-day-051.html",
            "4th-grade-day-51.html"
          ]
        },
        {
          "day": 52,
          "files": [
            "4th-grade-day-052.html",
            "4th-grade-day-52.html"
          ]
        },
        {
          "day": 53,
          "files": [
            "4th-grade-day-053.html",
            "4th-grade-day-53.html"
          ]
        },
        {
          "day": 54,
          "files": [
            "4th-grade-day-054.html",
            "4th-grade-day-54.html"
          ]
        },
        {
          "day": 55,
          "files": [
            "4th-grade-day-055.html",
            "4th-grade-day-55.html"
          ]
        },
        {
          "day": 56,
          "files": [
            "4th-grade-day-056.html",
            "4th-grade-day-56.html"
          ]
        },
        {
          "day": 57,
          "files": [
            "4th-grade-day-057.html",
            "4th-grade-day-57.html"
          ]
        },
        {
          "day": 58,
          "files": [
            "4th-grade-day-058.html",
            "4th-grade-day-58.html"
          ]
        },
        {
          "day": 59,
          "files": [
            "4th-grade-day-059.html",
            "4th-grade-day-59.html"
          ]
        },
        {
          "day": 60,
          "files": [
            "4th-grade-day-060.html",
            "4th-grade-day-60.html"
          ]
        }
      ]
    },
    "grade-5": {
      "uniqueDayCount": 182,
      "missing": [],
      "extras": [
        189,
        190
      ],
      "duplicateDayFiles": [
        {
          "day": 1,
          "files": [
            "5th-grade-day-001.html",
            "5th-grade-day-1.html"
          ]
        },
        {
          "day": 2,
          "files": [
            "5th-grade-day-002.html",
            "5th-grade-day-2.html"
          ]
        },
        {
          "day": 3,
          "files": [
            "5th-grade-day-003.html",
            "5th-grade-day-3.html"
          ]
        },
        {
          "day": 4,
          "files": [
            "5th-grade-day-004.html",
            "5th-grade-day-4.html"
          ]
        },
        {
          "day": 6,
          "files": [
            "5th-grade-day-006.html",
            "5th-grade-day-6.html"
          ]
        },
        {
          "day": 7,
          "files": [
            "5th-grade-day-007.html",
            "5th-grade-day-7.html"
          ]
        },
        {
          "day": 8,
          "files": [
            "5th-grade-day-008.html",
            "5th-grade-day-8.html"
          ]
        },
        {
          "day": 9,
          "files": [
            "5th-grade-day-009.html",
            "5th-grade-day-9.html"
          ]
        },
        {
          "day": 11,
          "files": [
            "5th-grade-day-011.html",
            "5th-grade-day-11.html"
          ]
        },
        {
          "day": 12,
          "files": [
            "5th-grade-day-012.html",
            "5th-grade-day-12.html"
          ]
        },
        {
          "day": 13,
          "files": [
            "5th-grade-day-013.html",
            "5th-grade-day-13.html"
          ]
        },
        {
          "day": 14,
          "files": [
            "5th-grade-day-014.html",
            "5th-grade-day-14.html"
          ]
        },
        {
          "day": 16,
          "files": [
            "5th-grade-day-016.html",
            "5th-grade-day-16.html"
          ]
        },
        {
          "day": 17,
          "files": [
            "5th-grade-day-017.html",
            "5th-grade-day-17.html"
          ]
        },
        {
          "day": 18,
          "files": [
            "5th-grade-day-018.html",
            "5th-grade-day-18.html"
          ]
        },
        {
          "day": 19,
          "files": [
            "5th-grade-day-019.html",
            "5th-grade-day-19.html"
          ]
        },
        {
          "day": 21,
          "files": [
            "5th-grade-day-021.html",
            "5th-grade-day-21.html"
          ]
        },
        {
          "day": 22,
          "files": [
            "5th-grade-day-022.html",
            "5th-grade-day-22.html"
          ]
        },
        {
          "day": 23,
          "files": [
            "5th-grade-day-023.html",
            "5th-grade-day-23.html"
          ]
        },
        {
          "day": 24,
          "files": [
            "5th-grade-day-024.html",
            "5th-grade-day-24.html"
          ]
        },
        {
          "day": 26,
          "files": [
            "5th-grade-day-026.html",
            "5th-grade-day-26.html"
          ]
        },
        {
          "day": 27,
          "files": [
            "5th-grade-day-027.html",
            "5th-grade-day-27.html"
          ]
        },
        {
          "day": 28,
          "files": [
            "5th-grade-day-028.html",
            "5th-grade-day-28.html"
          ]
        },
        {
          "day": 29,
          "files": [
            "5th-grade-day-029.html",
            "5th-grade-day-29.html"
          ]
        }
      ]
    },
    "grade-6": {
      "uniqueDayCount": 180,
      "missing": [],
      "extras": [],
      "duplicateDayFiles": [
        {
          "day": 1,
          "files": [
            "6th-grade-day-001.html",
            "6th-grade-day-1.html"
          ]
        },
        {
          "day": 2,
          "files": [
            "6th-grade-day-002.html",
            "6th-grade-day-2.html"
          ]
        },
        {
          "day": 3,
          "files": [
            "6th-grade-day-003.html",
            "6th-grade-day-3.html"
          ]
        },
        {
          "day": 4,
          "files": [
            "6th-grade-day-004.html",
            "6th-grade-day-4.html"
          ]
        }
      ]
    },
    "grade-7": {
      "uniqueDayCount": 0,
      "missing": [
        1,
        2,
        3,
        4,
        5,
        6,
        7,
        8,
        9,
        10,
        11,
        12,
        13,
        14,
        15,
        16,
        17,
        18,
        19,
        20,
        21,
        22,
        23,
        24,
        25,
        26,
        27,
        28,
        29,
        30,
        31,
        32,
        33,
        34,
        35,
        36,
        37,
        38,
        39,
        40,
        41,
        42,
        43,
        44,
        45,
        46,
        47,
        48,
        49,
        50,
        51,
        52,
        53,
        54,
        55,
        56,
        57,
        58,
        59,
        60,
        61,
        62,
        63,
        64,
        65,
        66,
        67,
        68,
        69,
        70,
        71,
        72,
        73,
        74,
        75,
        76,
        77,
        78,
        79,
        80,
        81,
        82,
        83,
        84,
        85,
        86,
        87,
        88,
        89,
        90,
        91,
        92,
        93,
        94,
        95,
        96,
        97,
        98,
        99,
        100,
        101,
        102,
        103,
        104,
        105,
        106,
        107,
        108,
        109,
        110,
        111,
        112,
        113,
        114,
        115,
        116,
        117,
        118,
        119,
        120,
        121,
        122,
        123,
        124,
        125,
        126,
        127,
        128,
        129,
        130,
        131,
        132,
        133,
        134,
        135,
        136,
        137,
        138,
        139,
        140,
        141,
        142,
        143,
        144,
        145,
        146,
        147,
        148,
        149,
        150,
        151,
        152,
        153,
        154,
        155,
        156,
        157,
        158,
        159,
        160,
        161,
        162,
        163,
        164,
        165,
        166,
        167,
        168,
        169,
        170,
        171,
        172,
        173,
        174,
        175,
        176,
        177,
        178,
        179,
        180
      ],
      "extras": [],
      "duplicateDayFiles": []
    },
    "grade-8": {
      "uniqueDayCount": 180,
      "missing": [],
      "extras": [],
      "duplicateDayFiles": []
    }
  },
  "cardReadiness": [
    {
      "id": "alice-wonderland",
      "grade": 4,
      "recommendedPocketId": "g4-p5-language-logic-opinion",
      "stage": "content-ready",
      "missingComponents": [],
      "notes": [
        "Library card sections completed for parent choice: reading, vocabulary, journals, writing, questions, informational text, and assessments.",
        "Created from local 4th grade source folder audit.",
        "Local 4th grade source folder includes complete adapted text, vocabulary file, comprehension questions, and image assets."
      ]
    },
    {
      "id": "anne-green-gables",
      "grade": 7,
      "recommendedPocketId": "g7-p1-imagination-belonging",
      "stage": "content-ready",
      "missingComponents": [],
      "notes": [
        "Launch-ready Grade 7 card with reading, vocabulary, journals, writing, questions, informational text, and assessments.",
        "Created from local 7th grade source folder audit.",
        "Source folder includes 24-chapter adapted text plus vocabulary and comprehension questions."
      ]
    },
    {
      "id": "arabian-nights",
      "grade": 7,
      "recommendedPocketId": "g7-p3-legends-world-tales",
      "stage": "content-ready",
      "missingComponents": [],
      "notes": [
        "Launch-ready Grade 7 card with reading, vocabulary, journals, writing, questions, informational text, and assessments.",
        "Created from local 7th grade source folder audit.",
        "Source folder includes 24-chapter adapted text plus vocabulary and comprehension questions."
      ]
    },
    {
      "id": "arabian-tales",
      "grade": 5,
      "recommendedPocketId": "g5-p3-world-tales",
      "stage": "content-ready",
      "missingComponents": [],
      "notes": [
        "Launch-ready Grade 5 card with reading, vocabulary, journals, writing, questions, informational text, and assessments.",
        "Created from local 5th grade source folder audit.",
        "Source folder includes Arabian tales, vocabulary spreadsheet, and comprehension questions."
      ]
    },
    {
      "id": "around-world-80-days",
      "grade": 4,
      "recommendedPocketId": "g4-p4-around-the-world",
      "stage": "missing-source",
      "missingComponents": [],
      "notes": [
        "Structured from existing markdown unit card."
      ]
    },
    {
      "id": "beowulf",
      "grade": 8,
      "recommendedPocketId": "g8-p4-epic-adventures",
      "stage": "content-ready",
      "missingComponents": [],
      "notes": [
        "Launch-ready Grade 8 card with reading, vocabulary, journals, writing, questions, informational text, and assessments.",
        "Structured from existing markdown unit card."
      ]
    },
    {
      "id": "call-of-wild-jungle-book",
      "grade": 4,
      "recommendedPocketId": "g4-p3-into-the-wild",
      "stage": "missing-source",
      "missingComponents": [],
      "notes": [
        "Structured from existing markdown unit card."
      ]
    },
    {
      "id": "celtic-mythology",
      "grade": 5,
      "recommendedPocketId": "g5-p3-world-tales",
      "stage": "content-ready",
      "missingComponents": [],
      "notes": [
        "Launch-ready Grade 5 card with reading, vocabulary, journals, writing, questions, informational text, and assessments.",
        "Created from local 5th grade source folder audit.",
        "Source folder includes Celtic mythology stories, vocabulary spreadsheet, and comprehension questions."
      ]
    },
    {
      "id": "cinderella",
      "grade": 3,
      "recommendedPocketId": "g3-p2-character",
      "stage": "content-ready",
      "missingComponents": [],
      "notes": [
        "Launch-ready Grade 3 card with reading, vocabulary, journals, writing, questions, informational text, and assessments.",
        "Created from local 3rd grade source folder audit.",
        "Source folder includes a 12-chapter text plus vocabulary and comprehension questions."
      ]
    },
    {
      "id": "connecticut-yankee",
      "grade": 6,
      "recommendedPocketId": "g6-p6-mastery",
      "stage": "content-ready",
      "missingComponents": [],
      "notes": [
        "Library card sections completed for parent assignment: reading, vocabulary, journals, writing, questions, informational text, and assessments.",
        "Created from local 6th grade source folder audit.",
        "Local source folder includes 18-chapter adapted text, vocabulary companion, and comprehension questions."
      ]
    },
    {
      "id": "dorian-gray",
      "grade": 8,
      "recommendedPocketId": "g8-p3-psychology-science",
      "stage": "content-ready",
      "missingComponents": [],
      "notes": [
        "Launch-ready Grade 8 card with reading, vocabulary, journals, writing, questions, informational text, and assessments.",
        "Structured from existing markdown unit card."
      ]
    },
    {
      "id": "dracula-young-readers",
      "grade": 5,
      "recommendedPocketId": "g5-p6-gothic-mastery",
      "stage": "content-ready",
      "missingComponents": [],
      "notes": [
        "Launch-ready Grade 5 card with reading, vocabulary, journals, writing, questions, informational text, and assessments.",
        "Created from local 5th grade source folder audit.",
        "Source folder includes Dracula young readers adaptation."
      ]
    },
    {
      "id": "egyptian-mythology",
      "grade": 5,
      "recommendedPocketId": "g5-p3-world-tales",
      "stage": "content-ready",
      "missingComponents": [],
      "notes": [
        "Launch-ready Grade 5 card with reading, vocabulary, journals, writing, questions, informational text, and assessments.",
        "Created from local 5th grade source folder audit.",
        "Source folder includes Egyptian mythology stories, vocabulary spreadsheet, and comprehension questions."
      ]
    },
    {
      "id": "elves-and-the-shoemaker",
      "grade": 3,
      "recommendedPocketId": "g3-p2-character",
      "stage": "content-ready",
      "missingComponents": [],
      "notes": [
        "Launch-ready Grade 3 card with reading, vocabulary, journals, writing, questions, informational text, and assessments.",
        "Created from local 3rd grade source folder audit.",
        "Source folder includes a 12-chapter text plus vocabulary and comprehension questions."
      ]
    },
    {
      "id": "frankenstein",
      "grade": 8,
      "recommendedPocketId": "g8-p3-psychology-science",
      "stage": "content-ready",
      "missingComponents": [],
      "notes": [
        "Launch-ready Grade 8 card with reading, vocabulary, journals, writing, questions, informational text, and assessments.",
        "Structured from existing markdown unit card."
      ]
    },
    {
      "id": "frankenstein-dracula",
      "grade": 5,
      "recommendedPocketId": "g5-p6-gothic-mastery",
      "stage": "content-ready",
      "missingComponents": [],
      "notes": [
        "Launch-ready Grade 5 card with reading, vocabulary, journals, writing, questions, informational text, and assessments.",
        "Created from local 5th grade source folder audit.",
        "Source folder includes young readers adaptations of Frankenstein and Dracula plus combined vocabulary spreadsheet."
      ]
    },
    {
      "id": "frankenstein-young-readers",
      "grade": 5,
      "recommendedPocketId": "g5-p6-gothic-mastery",
      "stage": "content-ready",
      "missingComponents": [],
      "notes": [
        "Launch-ready Grade 5 card with reading, vocabulary, journals, writing, questions, informational text, and assessments.",
        "Created from local 5th grade source folder audit.",
        "Source folder includes Frankenstein young readers adaptation."
      ]
    },
    {
      "id": "frog-prince",
      "grade": 3,
      "recommendedPocketId": "g3-p3-adventure",
      "stage": "content-ready",
      "missingComponents": [],
      "notes": [
        "Launch-ready Grade 3 card with reading, vocabulary, journals, writing, questions, informational text, and assessments.",
        "Created from local 3rd grade source folder audit.",
        "Source folder includes a 12-chapter text plus vocabulary and comprehension questions."
      ]
    },
    {
      "id": "g1-p1-foundations-card-shell",
      "grade": 1,
      "recommendedPocketId": "g1-p1-foundations",
      "stage": "needs-card",
      "missingComponents": [
        "readingSchedule",
        "vocabulary",
        "journals",
        "writing",
        "questions",
        "informationalTexts",
        "assessments"
      ],
      "notes": [
        "Generated to put this grade pocket into the Library Card format.",
        "Replace this shell with one or more real book/unit cards before generating daily lessons."
      ]
    },
    {
      "id": "g1-p2-folktales-card-shell",
      "grade": 1,
      "recommendedPocketId": "g1-p2-folktales",
      "stage": "needs-card",
      "missingComponents": [
        "readingSchedule",
        "vocabulary",
        "journals",
        "writing",
        "questions",
        "informationalTexts",
        "assessments"
      ],
      "notes": [
        "Generated to put this grade pocket into the Library Card format.",
        "Replace this shell with one or more real book/unit cards before generating daily lessons."
      ]
    },
    {
      "id": "g1-p3-animals-card-shell",
      "grade": 1,
      "recommendedPocketId": "g1-p3-animals",
      "stage": "needs-card",
      "missingComponents": [
        "readingSchedule",
        "vocabulary",
        "journals",
        "writing",
        "questions",
        "informationalTexts",
        "assessments"
      ],
      "notes": [
        "Generated to put this grade pocket into the Library Card format.",
        "Replace this shell with one or more real book/unit cards before generating daily lessons."
      ]
    },
    {
      "id": "g1-p4-community-card-shell",
      "grade": 1,
      "recommendedPocketId": "g1-p4-community",
      "stage": "needs-card",
      "missingComponents": [
        "readingSchedule",
        "vocabulary",
        "journals",
        "writing",
        "questions",
        "informationalTexts",
        "assessments"
      ],
      "notes": [
        "Generated to put this grade pocket into the Library Card format.",
        "Replace this shell with one or more real book/unit cards before generating daily lessons."
      ]
    },
    {
      "id": "g1-p5-imagination-card-shell",
      "grade": 1,
      "recommendedPocketId": "g1-p5-imagination",
      "stage": "needs-card",
      "missingComponents": [
        "readingSchedule",
        "vocabulary",
        "journals",
        "writing",
        "questions",
        "informationalTexts",
        "assessments"
      ],
      "notes": [
        "Generated to put this grade pocket into the Library Card format.",
        "Replace this shell with one or more real book/unit cards before generating daily lessons."
      ]
    },
    {
      "id": "g1-p6-mastery-card-shell",
      "grade": 1,
      "recommendedPocketId": "g1-p6-mastery",
      "stage": "needs-card",
      "missingComponents": [
        "readingSchedule",
        "vocabulary",
        "journals",
        "writing",
        "questions",
        "informationalTexts",
        "assessments"
      ],
      "notes": [
        "Generated to put this grade pocket into the Library Card format.",
        "Replace this shell with one or more real book/unit cards before generating daily lessons."
      ]
    },
    {
      "id": "greek-mythology",
      "grade": 5,
      "recommendedPocketId": "g5-p4-greek-roman",
      "stage": "content-ready",
      "missingComponents": [],
      "notes": [
        "Launch-ready Grade 5 card with reading, vocabulary, journals, writing, questions, informational text, and assessments.",
        "Created from local 5th grade source folder audit.",
        "Source folder includes Greek mythology stories plus vocabulary and comprehension documents."
      ]
    },
    {
      "id": "hansel-and-gretel",
      "grade": 3,
      "recommendedPocketId": "g3-p6-mastery",
      "stage": "content-ready",
      "missingComponents": [],
      "notes": [
        "Launch-ready Grade 3 card with reading, vocabulary, journals, writing, questions, informational text, and assessments.",
        "Created from local 3rd grade source folder audit.",
        "Source folder includes a 12-chapter text plus vocabulary and comprehension questions."
      ]
    },
    {
      "id": "heidi",
      "grade": 3,
      "recommendedPocketId": "g3-p5-realistic",
      "stage": "content-ready",
      "missingComponents": [],
      "notes": [
        "Launch-ready Grade 3 card with reading, vocabulary, journals, writing, questions, informational text, and assessments.",
        "Created from local 3rd grade source folder audit.",
        "Source folder includes a 12-chapter text plus vocabulary and comprehension questions."
      ]
    },
    {
      "id": "hunchback",
      "grade": 4,
      "recommendedPocketId": "g4-p4-around-the-world",
      "stage": "content-ready",
      "missingComponents": [],
      "notes": [
        "Library card sections completed for parent choice: reading, vocabulary, journals, writing, questions, informational text, and assessments.",
        "Created from local 4th grade source folder audit.",
        "Local 4th grade source folder includes 24-chapter adapted text plus vocabulary and comprehension questions."
      ]
    },
    {
      "id": "invisible-man",
      "grade": 8,
      "recommendedPocketId": "g8-p1-science-adventure",
      "stage": "content-ready",
      "missingComponents": [],
      "notes": [
        "Launch-ready Grade 8 card with reading, vocabulary, journals, writing, questions, informational text, and assessments."
      ]
    },
    {
      "id": "jack-and-the-beanstalk",
      "grade": 3,
      "recommendedPocketId": "g3-p3-adventure",
      "stage": "content-ready",
      "missingComponents": [],
      "notes": [
        "Launch-ready Grade 3 card with reading, vocabulary, journals, writing, questions, informational text, and assessments.",
        "Created from local 3rd grade source folder audit.",
        "Source folder includes a 12-chapter text plus vocabulary and comprehension questions."
      ]
    },
    {
      "id": "jack-be-nimble",
      "grade": 2,
      "recommendedPocketId": "g2-p1-fluency",
      "stage": "content-ready",
      "missingComponents": [],
      "notes": [
        "Integrated from the real Grade 2 Quarter 1, Book 6 source file.",
        "Early card: shorter text, short sentences, easiest independent start."
      ]
    },
    {
      "id": "jekyll-hyde",
      "grade": 8,
      "recommendedPocketId": "g8-p3-psychology-science",
      "stage": "content-ready",
      "missingComponents": [],
      "notes": [
        "Launch-ready Grade 8 card with reading, vocabulary, journals, writing, questions, informational text, and assessments.",
        "Structured from existing markdown unit card."
      ]
    },
    {
      "id": "journey-center-earth",
      "grade": 6,
      "recommendedPocketId": "g6-p5-science-adventure",
      "stage": "content-ready",
      "missingComponents": [],
      "notes": [
        "Library card sections completed for parent assignment: reading, vocabulary, journals, writing, questions, informational text, and assessments.",
        "Created from local 6th grade source folder audit.",
        "Local source folder includes 24-chapter adapted text, vocabulary companion, comprehension questions, and writing/journal signals."
      ]
    },
    {
      "id": "kidnapped",
      "grade": 7,
      "recommendedPocketId": "g7-p5-journeys-sea",
      "stage": "content-ready",
      "missingComponents": [],
      "notes": [
        "Launch-ready Grade 7 card with reading, vocabulary, journals, writing, questions, informational text, and assessments.",
        "Created from local 7th grade source folder audit.",
        "Source folder includes 24-chapter adapted text plus vocabulary and comprehension questions."
      ]
    },
    {
      "id": "king-arthur",
      "grade": 5,
      "recommendedPocketId": "g5-p2-king-arthur",
      "stage": "content-ready",
      "missingComponents": [],
      "notes": [
        "Launch-ready Grade 5 card with reading, vocabulary, journals, writing, questions, informational text, and assessments.",
        "Created from local 5th grade source folder audit.",
        "Source folder includes King Arthur young adult edition plus vocabulary and comprehension document."
      ]
    },
    {
      "id": "lost-world",
      "grade": 8,
      "recommendedPocketId": "g8-p1-science-adventure",
      "stage": "content-ready",
      "missingComponents": [],
      "notes": [
        "Launch-ready Grade 8 card with reading, vocabulary, journals, writing, questions, informational text, and assessments.",
        "Structured from existing markdown unit card."
      ]
    },
    {
      "id": "moby-dick",
      "grade": 7,
      "recommendedPocketId": "g7-p6-mastery-classics",
      "stage": "content-ready",
      "missingComponents": [],
      "notes": [
        "Launch-ready Grade 7 card with reading, vocabulary, journals, writing, questions, informational text, and assessments.",
        "Created from local 7th grade source folder audit.",
        "Source folder includes 24-chapter adapted text plus vocabulary and comprehension questions."
      ]
    },
    {
      "id": "monte-cristo",
      "grade": 8,
      "recommendedPocketId": "g8-p4-epic-adventures",
      "stage": "content-ready",
      "missingComponents": [],
      "notes": [
        "Launch-ready Grade 8 card with reading, vocabulary, journals, writing, questions, informational text, and assessments.",
        "Structured from existing markdown unit card."
      ]
    },
    {
      "id": "mysterious-island",
      "grade": 8,
      "recommendedPocketId": "g8-p2-survival-engineering",
      "stage": "content-ready",
      "missingComponents": [],
      "notes": [
        "Launch-ready Grade 8 card with reading, vocabulary, journals, writing, questions, informational text, and assessments.",
        "Structured from existing markdown unit card."
      ]
    },
    {
      "id": "norse-mythology",
      "grade": 5,
      "recommendedPocketId": "g5-p5-norse",
      "stage": "content-ready",
      "missingComponents": [],
      "notes": [
        "Launch-ready Grade 5 card with reading, vocabulary, journals, writing, questions, informational text, and assessments.",
        "Created from local 5th grade source folder audit.",
        "Source folder includes Norse mythology stories, vocabulary files, and comprehension questions."
      ]
    },
    {
      "id": "odyssey",
      "grade": 6,
      "recommendedPocketId": "g6-p6-mastery",
      "stage": "content-ready",
      "missingComponents": [],
      "notes": [
        "Library card sections completed for parent assignment: reading, vocabulary, journals, writing, questions, informational text, and assessments.",
        "Created from local 6th grade source folder audit.",
        "Local source folder includes a 24-chapter adapted epic text. Vocabulary, questions, journals, and assessments are supplied by the generated library card sections until companion docs are added."
      ]
    },
    {
      "id": "princess-goblin",
      "grade": 6,
      "recommendedPocketId": "g6-p3-fantasy",
      "stage": "content-ready",
      "missingComponents": [],
      "notes": [
        "Library card sections completed for parent assignment: reading, vocabulary, journals, writing, questions, informational text, and assessments.",
        "Created from local 6th grade source folder audit.",
        "Local source folder includes 18-chapter adapted text, vocabulary companion, and comprehension questions."
      ]
    },
    {
      "id": "puss-in-boots",
      "grade": 2,
      "recommendedPocketId": "g2-p4-nature",
      "stage": "content-ready",
      "missingComponents": [],
      "notes": [
        "Integrated from the real Grade 2 Quarter 3, Book 18 source file.",
        "Advanced card: longest texts and/or more complex sentence structure."
      ]
    },
    {
      "id": "rapunzel",
      "grade": 3,
      "recommendedPocketId": "g3-p4-fantasy",
      "stage": "content-ready",
      "missingComponents": [],
      "notes": [
        "Launch-ready Grade 3 card with reading, vocabulary, journals, writing, questions, informational text, and assessments.",
        "Created from local 3rd grade source folder audit.",
        "Source folder includes a 12-chapter text plus vocabulary and comprehension questions."
      ]
    },
    {
      "id": "red-badge-courage",
      "grade": 7,
      "recommendedPocketId": "g7-p4-survival-courage",
      "stage": "content-ready",
      "missingComponents": [],
      "notes": [
        "Launch-ready Grade 7 card with reading, vocabulary, journals, writing, questions, informational text, and assessments.",
        "Created from local 7th grade source folder audit.",
        "Source folder includes 24-chapter adapted text plus vocabulary and comprehension questions."
      ]
    },
    {
      "id": "robin-hood",
      "grade": 6,
      "recommendedPocketId": "g6-p2-adventure",
      "stage": "content-ready",
      "missingComponents": [],
      "notes": [
        "Library card sections completed for parent assignment: reading, vocabulary, journals, writing, questions, informational text, and assessments.",
        "Created from local 6th grade source folder audit.",
        "Local source folder includes 24-chapter adapted text, vocabulary companion, comprehension questions, and plain-text exports."
      ]
    },
    {
      "id": "robin-hood-5",
      "grade": 5,
      "recommendedPocketId": "g5-p1-robin-hood",
      "stage": "content-ready",
      "missingComponents": [],
      "notes": [
        "Launch-ready Grade 5 card with reading, vocabulary, journals, writing, questions, informational text, and assessments.",
        "Created from local 5th grade source folder audit.",
        "Source folder includes Robin Hood young readers text plus vocabulary and comprehension document."
      ]
    },
    {
      "id": "roman-mythology",
      "grade": 5,
      "recommendedPocketId": "g5-p4-greek-roman",
      "stage": "content-ready",
      "missingComponents": [],
      "notes": [
        "Launch-ready Grade 5 card with reading, vocabulary, journals, writing, questions, informational text, and assessments.",
        "Created from local 5th grade source folder audit.",
        "Source folder includes Roman mythology stories plus vocabulary and comprehension documents."
      ]
    },
    {
      "id": "secret-garden",
      "grade": 4,
      "recommendedPocketId": "g4-p6-mastery-capstone",
      "stage": "content-ready",
      "missingComponents": [],
      "notes": [
        "Library card sections completed for parent choice: reading, vocabulary, journals, writing, questions, informational text, and assessments.",
        "Created from local 4th grade source folder audit.",
        "Local 4th grade source folder includes complete adapted text, vocabulary file, and comprehension questions."
      ]
    },
    {
      "id": "secret-garden",
      "grade": 7,
      "recommendedPocketId": "g7-p2-gardens-growth",
      "stage": "content-ready",
      "missingComponents": [],
      "notes": [
        "Launch-ready Grade 7 card with reading, vocabulary, journals, writing, questions, informational text, and assessments.",
        "Created from local 7th grade source folder audit.",
        "Source folder includes 24-chapter adapted text plus vocabulary and comprehension questions."
      ]
    },
    {
      "id": "sherlock-holmes",
      "grade": 8,
      "recommendedPocketId": "g8-p4-epic-adventures",
      "stage": "content-ready",
      "missingComponents": [],
      "notes": [
        "Launch-ready Grade 8 card with reading, vocabulary, journals, writing, questions, informational text, and assessments.",
        "Structured from existing markdown unit card."
      ]
    },
    {
      "id": "simple-simon",
      "grade": 2,
      "recommendedPocketId": "g2-p5-adventure",
      "stage": "content-ready",
      "missingComponents": [],
      "notes": [
        "Integrated from the real Grade 2 Quarter 4, Book 24 source file.",
        "Advanced card: longest texts and/or more complex sentence structure."
      ]
    },
    {
      "id": "sinbad",
      "grade": 4,
      "recommendedPocketId": "g4-p3-into-the-wild",
      "stage": "content-ready",
      "missingComponents": [],
      "notes": [
        "Library card sections completed for parent choice: reading, vocabulary, journals, writing, questions, informational text, and assessments.",
        "Created from local 4th grade source folder audit.",
        "Local 4th grade source folder includes 24-chapter Sinbad text plus vocabulary and comprehension questions."
      ]
    },
    {
      "id": "snow-queen",
      "grade": 3,
      "recommendedPocketId": "g3-p4-fantasy",
      "stage": "content-ready",
      "missingComponents": [],
      "notes": [
        "Launch-ready Grade 3 card with reading, vocabulary, journals, writing, questions, informational text, and assessments.",
        "Created from local 3rd grade source folder audit.",
        "Source folder includes a 12-chapter text plus vocabulary and comprehension questions."
      ]
    },
    {
      "id": "stone-soup",
      "grade": 2,
      "recommendedPocketId": "g2-p1-fluency",
      "stage": "content-ready",
      "missingComponents": [],
      "notes": [
        "Integrated from the real Grade 2 Quarter 1, Book 4 source file.",
        "Early card: shorter text, short sentences, easiest independent start."
      ]
    },
    {
      "id": "swiss-family-robinson",
      "grade": 6,
      "recommendedPocketId": "g6-p4-journeys",
      "stage": "content-ready",
      "missingComponents": [],
      "notes": [
        "Library card sections completed for parent assignment: reading, vocabulary, journals, writing, questions, informational text, and assessments.",
        "Created from local 6th grade source folder audit.",
        "Local source folder includes 24-chapter adapted text, vocabulary companion, comprehension questions, and plain-text exports."
      ]
    },
    {
      "id": "the-brave-little-tailor",
      "grade": 2,
      "recommendedPocketId": "g2-p2-fables",
      "stage": "content-ready",
      "missingComponents": [],
      "notes": [
        "Integrated from the real Grade 2 Quarter 2, Book 10 source file.",
        "Developing card: moderate length with more vocabulary and plot detail."
      ]
    },
    {
      "id": "the-bundle-of-sticks",
      "grade": 2,
      "recommendedPocketId": "g2-p4-nature",
      "stage": "content-ready",
      "missingComponents": [],
      "notes": [
        "Integrated from the real Grade 2 Quarter 3, Book 16 source file.",
        "Advanced card: longest texts and/or more complex sentence structure."
      ]
    },
    {
      "id": "the-cat-and-the-mice",
      "grade": 2,
      "recommendedPocketId": "g2-p2-fables",
      "stage": "content-ready",
      "missingComponents": [],
      "notes": [
        "Integrated from the real Grade 2 Quarter 2, Book 11 source file.",
        "Strong Reader card: longer text and more inferential fable work."
      ]
    },
    {
      "id": "the-crow-and-the-pitcher",
      "grade": 2,
      "recommendedPocketId": "g2-p2-fables",
      "stage": "content-ready",
      "missingComponents": [],
      "notes": [
        "Integrated from the real Grade 2 Quarter 2, Book 8 source file.",
        "Strong Reader card: longer text and more inferential fable work."
      ]
    },
    {
      "id": "the-dog-and-his-reflection",
      "grade": 2,
      "recommendedPocketId": "g2-p2-fables",
      "stage": "content-ready",
      "missingComponents": [],
      "notes": [
        "Integrated from the real Grade 2 Quarter 2, Book 9 source file.",
        "Strong Reader card: longer text and more inferential fable work."
      ]
    },
    {
      "id": "the-farmer-and-the-stork",
      "grade": 2,
      "recommendedPocketId": "g2-p2-fables",
      "stage": "content-ready",
      "missingComponents": [],
      "notes": [
        "Integrated from the real Grade 2 Quarter 2, Book 12 source file.",
        "Strong Reader card: longer text and more inferential fable work."
      ]
    },
    {
      "id": "the-gingerbread-house",
      "grade": 2,
      "recommendedPocketId": "g2-p1-fluency",
      "stage": "content-ready",
      "missingComponents": [],
      "notes": [
        "Integrated from the real Grade 2 Quarter 1, Book 3 source file.",
        "Early card: shorter text, short sentences, easiest independent start."
      ]
    },
    {
      "id": "the-goose-that-laid-the-golden-eggs",
      "grade": 2,
      "recommendedPocketId": "g2-p4-nature",
      "stage": "content-ready",
      "missingComponents": [],
      "notes": [
        "Integrated from the real Grade 2 Quarter 3, Book 17 source file.",
        "Advanced card: longest texts and/or more complex sentence structure."
      ]
    },
    {
      "id": "the-lion-and-the-lamb",
      "grade": 2,
      "recommendedPocketId": "g2-p2-fables",
      "stage": "content-ready",
      "missingComponents": [],
      "notes": [
        "Integrated from the real Grade 2 Quarter 2, Book 7 source file.",
        "Advanced card: longest texts and/or more complex sentence structure."
      ]
    },
    {
      "id": "the-little-engine-that-could",
      "grade": 2,
      "recommendedPocketId": "g2-p1-fluency",
      "stage": "content-ready",
      "missingComponents": [],
      "notes": [
        "Integrated from the real Grade 2 Quarter 1, Book 2 source file.",
        "Early card: shorter text, short sentences, easiest independent start."
      ]
    },
    {
      "id": "the-little-match-girl",
      "grade": 2,
      "recommendedPocketId": "g2-p2-fables",
      "stage": "content-ready",
      "missingComponents": [],
      "notes": [
        "Integrated from the real Grade 2 Quarter 2, Book 11 source file.",
        "Developing card: moderate length with more vocabulary and plot detail."
      ]
    },
    {
      "id": "the-milkmaid-and-her-pail",
      "grade": 2,
      "recommendedPocketId": "g2-p4-nature",
      "stage": "content-ready",
      "missingComponents": [],
      "notes": [
        "Integrated from the real Grade 2 Quarter 3, Book 13 source file.",
        "Strong Reader card: longer text and more inferential fable work."
      ]
    },
    {
      "id": "the-oak-and-the-reed",
      "grade": 2,
      "recommendedPocketId": "g2-p4-nature",
      "stage": "content-ready",
      "missingComponents": [],
      "notes": [
        "Integrated from the real Grade 2 Quarter 3, Book 14 source file.",
        "Strong Reader card: longer text and more inferential fable work."
      ]
    },
    {
      "id": "the-old-woman-who-lived-in-a-shoe",
      "grade": 2,
      "recommendedPocketId": "g2-p1-fluency",
      "stage": "content-ready",
      "missingComponents": [],
      "notes": [
        "Integrated from the real Grade 2 Quarter 1, Book 5 source file.",
        "Early card: shorter text, short sentences, easiest independent start."
      ]
    },
    {
      "id": "the-shepherd-boy-and-the-wolf",
      "grade": 2,
      "recommendedPocketId": "g2-p4-nature",
      "stage": "content-ready",
      "missingComponents": [],
      "notes": [
        "Integrated from the real Grade 2 Quarter 3, Book 15 source file.",
        "Strong Reader card: longer text and more inferential fable work."
      ]
    },
    {
      "id": "the-tale-of-benjamin-bunny",
      "grade": 2,
      "recommendedPocketId": "g2-p2-fables",
      "stage": "content-ready",
      "missingComponents": [],
      "notes": [
        "Integrated from the real Grade 2 Quarter 2, Book 7 source file.",
        "Early card: shorter text, short sentences, easiest independent start."
      ]
    },
    {
      "id": "the-tale-of-jemima-puddle-duck",
      "grade": 2,
      "recommendedPocketId": "g2-p5-adventure",
      "stage": "content-ready",
      "missingComponents": [],
      "notes": [
        "Integrated from the real Grade 2 Quarter 4, Book 20 source file.",
        "Advanced card: longest texts and/or more complex sentence structure."
      ]
    },
    {
      "id": "the-tale-of-mr-jeremy-fisher",
      "grade": 2,
      "recommendedPocketId": "g2-p5-adventure",
      "stage": "content-ready",
      "missingComponents": [],
      "notes": [
        "Integrated from the real Grade 2 Quarter 4, Book 22 source file.",
        "Advanced card: longest texts and/or more complex sentence structure."
      ]
    },
    {
      "id": "the-tale-of-mrs-tiggy-winkle",
      "grade": 2,
      "recommendedPocketId": "g2-p2-fables",
      "stage": "content-ready",
      "missingComponents": [],
      "notes": [
        "Integrated from the real Grade 2 Quarter 2, Book 9 source file.",
        "Developing card: moderate length with more vocabulary and plot detail."
      ]
    },
    {
      "id": "the-tale-of-peter-rabbit",
      "grade": 2,
      "recommendedPocketId": "g2-p5-adventure",
      "stage": "content-ready",
      "missingComponents": [],
      "notes": [
        "Integrated from the real Grade 2 Quarter 4, Book 21 source file.",
        "Advanced card: longest texts and/or more complex sentence structure."
      ]
    },
    {
      "id": "the-tale-of-squirrel-nutkin",
      "grade": 2,
      "recommendedPocketId": "g2-p5-adventure",
      "stage": "content-ready",
      "missingComponents": [],
      "notes": [
        "Integrated from the real Grade 2 Quarter 4, Book 19 source file.",
        "Advanced card: longest texts and/or more complex sentence structure."
      ]
    },
    {
      "id": "the-tale-of-tom-kitten",
      "grade": 2,
      "recommendedPocketId": "g2-p2-fables",
      "stage": "content-ready",
      "missingComponents": [],
      "notes": [
        "Integrated from the real Grade 2 Quarter 2, Book 8 source file.",
        "Developing card: moderate length with more vocabulary and plot detail."
      ]
    },
    {
      "id": "the-three-little-kittens",
      "grade": 2,
      "recommendedPocketId": "g2-p1-fluency",
      "stage": "content-ready",
      "missingComponents": [],
      "notes": [
        "Integrated from the real Grade 2 Quarter 1, Book 1 source file.",
        "Early card: shorter text, short sentences, easiest independent start."
      ]
    },
    {
      "id": "the-wind-and-the-sun",
      "grade": 2,
      "recommendedPocketId": "g2-p2-fables",
      "stage": "content-ready",
      "missingComponents": [],
      "notes": [
        "Integrated from the real Grade 2 Quarter 2, Book 10 source file.",
        "Strong Reader card: longer text and more inferential fable work."
      ]
    },
    {
      "id": "three-musketeers",
      "grade": 4,
      "recommendedPocketId": "g4-p2-adventure-pov",
      "stage": "content-ready",
      "missingComponents": [],
      "notes": [
        "Library card sections completed for parent choice: reading, vocabulary, journals, writing, questions, informational text, and assessments.",
        "Created from local 4th grade source folder audit.",
        "Local 4th grade source folder includes a complete adapted text, vocabulary file, comprehension questions, and image asset."
      ]
    },
    {
      "id": "thumbelina",
      "grade": 2,
      "recommendedPocketId": "g2-p2-fables",
      "stage": "content-ready",
      "missingComponents": [],
      "notes": [
        "Integrated from the real Grade 2 Quarter 2, Book 12 source file.",
        "Developing card: moderate length with more vocabulary and plot detail."
      ]
    },
    {
      "id": "thumbelina",
      "grade": 3,
      "recommendedPocketId": "g3-p4-fantasy",
      "stage": "content-ready",
      "missingComponents": [],
      "notes": [
        "Launch-ready Grade 3 card with reading, vocabulary, journals, writing, questions, informational text, and assessments.",
        "Created from local 3rd grade source folder audit.",
        "Source folder includes a 12-chapter text plus vocabulary and comprehension questions."
      ]
    },
    {
      "id": "time-machine",
      "grade": 8,
      "recommendedPocketId": "g8-p2-survival-engineering",
      "stage": "content-ready",
      "missingComponents": [],
      "notes": [
        "Launch-ready Grade 8 card with reading, vocabulary, journals, writing, questions, informational text, and assessments.",
        "Structured from existing markdown unit card."
      ]
    },
    {
      "id": "tom-sawyer",
      "grade": 6,
      "recommendedPocketId": "g6-p1-tom-sawyer",
      "stage": "content-ready",
      "missingComponents": [],
      "notes": [
        "Library card sections completed for parent assignment: reading, vocabulary, journals, writing, questions, informational text, and assessments.",
        "Structured from existing markdown unit card."
      ]
    },
    {
      "id": "treasure-island",
      "grade": 4,
      "recommendedPocketId": "g4-p2-adventure-pov",
      "stage": "missing-source",
      "missingComponents": [],
      "notes": [
        "Structured from existing markdown unit card.",
        "Official 4th grade scope card, but the local source files are not present yet. Keep hidden from parent choice until the story, vocabulary, questions, and writing materials exist."
      ]
    },
    {
      "id": "turn-of-the-screw",
      "grade": 8,
      "recommendedPocketId": "g8-p2-survival-engineering",
      "stage": "content-ready",
      "missingComponents": [],
      "notes": [
        "Launch-ready Grade 8 card with reading, vocabulary, journals, writing, questions, informational text, and assessments.",
        "Created from local 8th grade source folder audit.",
        "Source folder includes chapter markdown files and a complete vocabulary file."
      ]
    },
    {
      "id": "twelve-dancing-princesses",
      "grade": 3,
      "recommendedPocketId": "g3-p3-adventure",
      "stage": "content-ready",
      "missingComponents": [],
      "notes": [
        "Launch-ready Grade 3 card with reading, vocabulary, journals, writing, questions, informational text, and assessments.",
        "Created from local 3rd grade source folder audit.",
        "Source folder includes a 12-chapter text plus vocabulary and comprehension questions."
      ]
    },
    {
      "id": "twenty-thousand-leagues",
      "grade": 6,
      "recommendedPocketId": "g6-p5-science-adventure",
      "stage": "content-ready",
      "missingComponents": [],
      "notes": [
        "Library card sections completed for parent assignment: reading, vocabulary, journals, writing, questions, informational text, and assessments.",
        "Created from local 6th grade source folder audit.",
        "Local source folder includes 24-chapter adapted text, vocabulary companion, and comprehension questions."
      ]
    },
    {
      "id": "twenty-thousand-leagues-7",
      "grade": 7,
      "recommendedPocketId": "g7-p5-journeys-sea",
      "stage": "content-ready",
      "missingComponents": [],
      "notes": [
        "Launch-ready Grade 7 card with reading, vocabulary, journals, writing, questions, informational text, and assessments.",
        "Created from local 7th grade source folder audit.",
        "Source folder includes 24 chapters in markdown plus a complete vocabulary file."
      ]
    },
    {
      "id": "ugly-duckling",
      "grade": 3,
      "recommendedPocketId": "g3-p1-classic-launch",
      "stage": "content-ready",
      "missingComponents": [],
      "notes": [
        "Launch-ready Grade 3 card with reading, vocabulary, journals, writing, questions, informational text, and assessments.",
        "Created from local 3rd grade source folder audit.",
        "Source folder includes a 12-chapter text plus vocabulary and comprehension questions."
      ]
    },
    {
      "id": "velveteen-rabbit",
      "grade": 3,
      "recommendedPocketId": "g3-p1-classic-launch",
      "stage": "content-ready",
      "missingComponents": [],
      "notes": [
        "Launch-ready Grade 3 card with reading, vocabulary, journals, writing, questions, informational text, and assessments.",
        "Created from local 3rd grade source folder audit.",
        "Source folder includes a 12-chapter text plus vocabulary and comprehension questions."
      ]
    },
    {
      "id": "war-of-worlds",
      "grade": 8,
      "recommendedPocketId": "g8-p1-science-adventure",
      "stage": "content-ready",
      "missingComponents": [],
      "notes": [
        "Launch-ready Grade 8 card with reading, vocabulary, journals, writing, questions, informational text, and assessments.",
        "Structured from existing markdown unit card."
      ]
    },
    {
      "id": "wizard-of-oz",
      "grade": 4,
      "recommendedPocketId": "g4-p1-hero-journey",
      "stage": "content-ready",
      "missingComponents": [],
      "notes": [
        "Library card sections completed for parent choice: reading, vocabulary, journals, writing, questions, informational text, and assessments.",
        "Created from local 4th grade source folder audit.",
        "Local 4th grade source folder includes a 24-chapter Oz adaptation, workbook, vocabulary guide, comprehension questions, and image/PDF assets."
      ]
    }
  ]
}
